autodoc2/__init__.py
autodoc2/analysis.py
autodoc2/astroid_utils.py
autodoc2/cli.py
autodoc2/config.py
autodoc2/db.py
autodoc2/py.typed
autodoc2/resolve_all.py
autodoc2/utils.py
autodoc2/render/__init__.py
autodoc2/render/base.py
autodoc2/render/myst_.py
autodoc2/render/rst_.py
autodoc2/sphinx/__init__.py
autodoc2/sphinx/autodoc.py
autodoc2/sphinx/docstring.py
autodoc2/sphinx/extension.py
autodoc2/sphinx/summary.py
autodoc2/sphinx/utils.py
sphinx_autodoc2-0.5.0.dist-info/entry_points.txt
sphinx_autodoc2-0.5.0.dist-info/LICENSE
sphinx_autodoc2-0.5.0.dist-info/WHEEL
sphinx_autodoc2-0.5.0.dist-info/METADATA
sphinx_autodoc2-0.5.0.dist-info/RECORD
